metaflow_extensions/magicdir/plugins/__init__.py
metaflow_plugin_magicdir-0.0.4.dist-info/METADATA
metaflow_plugin_magicdir-0.0.4.dist-info/WHEEL
metaflow_plugin_magicdir-0.0.4.dist-info/top_level.txt
metaflow_plugin_magicdir-0.0.4.dist-info/RECORD
