Metadata-Version: 2.1
Name: metaflow-plugin-magicdir
Version: 0.0.4
Summary: Pass directories between metaflow steps.
Home-page: https://github.com/outerbounds/metaflow-plugin-magicdir
Author: Hamel Husain
Author-email: hamel.husain@gmail.com
License: Apache Software License
Platform: UNKNOWN
Requires-Dist: metaflow (>=2.5.0)
